{"index":{"0":5,"1":9,"2":11,"3":14,"4":24,"5":25,"6":33,"7":34,"8":39,"9":101,"10":121,"11":129,"12":132,"13":157,"14":161},"artist":{"0":"Taylor Swift","1":"Taylor Swift","2":"Taylor Swift","3":"Taylor Swift","4":"Taylor Swift","5":"Taylor Swift","6":"Taylor Swift","7":"Taylor Swift","8":"Taylor Swift","9":"Taylor Swift","10":"Taylor Swift","11":"Taylor Swift","12":"Taylor Swift","13":"Taylor Swift","14":"Taylor Swift"},"title":{"0":"Look What You Made Me Do","1":"You Need To Calm Down","2":"Blank Space","3":"\u200bmy tears ricochet","4":"\u200billicit affairs","5":"\u200bthis is me trying","6":"\u200bmad woman","7":"\u200bivy","8":"\u200bno body, no crime","9":"Treacherous","10":"Mean","11":"Picture to Burn","12":"The Way I Loved You","13":"Girl at Home","14":"Let\u2019s Go (Battle)"},"negative":{"0":0.115,"1":0.087,"2":0.149,"3":0.184,"4":0.139,"5":0.102,"6":0.26,"7":0.163,"8":0.1,"9":0.09,"10":0.089,"11":0.301,"12":0.126,"13":0.069,"14":0.156},"neutral":{"0":0.816,"1":0.724,"2":0.688,"3":0.696,"4":0.803,"5":0.832,"6":0.663,"7":0.704,"8":0.795,"9":0.84,"10":0.881,"11":0.634,"12":0.648,"13":0.848,"14":0.732},"positive":{"0":0.069,"1":0.189,"2":0.163,"3":0.121,"4":0.059,"5":0.066,"6":0.076,"7":0.134,"8":0.105,"9":0.07,"10":0.03,"11":0.064,"12":0.226,"13":0.083,"14":0.112},"compound":{"0":-0.9798,"1":0.9911,"2":0.8537,"3":-0.9793,"4":-0.9754,"5":-0.8606,"6":-0.9971,"7":-0.9488,"8":0.5093,"9":-0.5777,"10":-0.9851,"11":-0.998,"12":0.9955,"13":0.1927,"14":-0.9797},"sentiment_type":{"0":"NEGATIVE","1":"POSITIVE","2":"POSITIVE","3":"NEGATIVE","4":"NEGATIVE","5":"NEGATIVE","6":"NEGATIVE","7":"NEGATIVE","8":"POSITIVE","9":"NEGATIVE","10":"NEGATIVE","11":"NEGATIVE","12":"POSITIVE","13":"NEUTRAL","14":"NEGATIVE"},"joy":{"0":2,"1":4,"2":24,"3":3,"4":3,"5":0,"6":3,"7":2,"8":4,"9":4,"10":3,"11":5,"12":10,"13":1,"14":7},"anger":{"0":7,"1":5,"2":25,"3":11,"4":11,"5":5,"6":26,"7":13,"8":8,"9":10,"10":6,"11":23,"12":15,"13":3,"14":15},"sadness":{"0":5,"1":5,"2":21,"3":6,"4":9,"5":4,"6":23,"7":9,"8":6,"9":0,"10":6,"11":15,"12":4,"13":3,"14":14},"emotion":{"0":"anger","1":"anger","2":"anger","3":"anger","4":"anger","5":"anger","6":"anger","7":"anger","8":"anger","9":"anger","10":"anger","11":"anger","12":"anger","13":"anger","14":"anger"}}